tmd_layer/__init__.py
tmd_layer/tmd_layer.py
tmd_layer-0.0.2.dist-info/LICENSE
tmd_layer-0.0.2.dist-info/METADATA
tmd_layer-0.0.2.dist-info/WHEEL
tmd_layer-0.0.2.dist-info/top_level.txt
tmd_layer-0.0.2.dist-info/RECORD
